{
  "team_slug": "grand-falls-rapids",
  "team_name": "Grand-Falls-Rapids",
  "league": "MHL",
  "season": "2024-25",
  "season_id": 41,
  "team_id": 12,
  "updated_at": "2026-02-05T07:32:37.424Z",
  "player_count": 24,
  "players": [
    {
      "player_id": "mhl-3552",
      "number": "2",
      "first_name": "William",
      "last_name": "Patey",
      "name": "William Patey",
      "position": "RD",
      "height": "6'0",
      "height_inches": 72,
      "weight": 180,
      "shoots": "R",
      "birthdate": "2006-08-18",
      "birth_year": "'06",
      "age": 20,
      "hometown": "Cow Head, NL",
      "birthplace": "Cow Head, NL, ",
      "rookie": false,
      "veteran": false,
      "headshot": "assets/headshots/Grand-Falls-Rapids/2-william-patey.jpg",
      "headshot_url": "https://assets.leaguestat.com/mhl/240x240/3552.jpg",
      "stats": {},
      "hockeytech_id": "3552",
      "person_id": "4134",
      "flags": []
    },
    {
      "player_id": "mhl-3806",
      "number": "4",
      "first_name": "Loic",
      "last_name": "Gallant",
      "name": "Loic Gallant",
      "position": "D",
      "height": "6'1",
      "height_inches": 73,
      "weight": 192,
      "shoots": "R",
      "birthdate": "2007-02-14",
      "birth_year": "'07",
      "age": 19,
      "hometown": "Rimouski, QC",
      "birthplace": "Rimouski, QC, ",
      "rookie": true,
      "veteran": false,
      "headshot": "assets/headshots/Grand-Falls-Rapids/4-loic-gallant.jpg",
      "headshot_url": "https://assets.leaguestat.com/mhl/240x240/3806.jpg",
      "stats": {
        "games_played": 36,
        "goals": 0,
        "assists": 11,
        "points": 11,
        "plus_minus": 0,
        "penalty_minutes": 45,
        "power_play_goals": 0,
        "power_play_assists": 3,
        "power_play_points": 3,
        "short_handed_goals": 0,
        "short_handed_assists": 0,
        "short_handed_points": 0,
        "game_winning_goals": 0,
        "overtime_goals": 0,
        "points_per_game": 0.31
      },
      "hockeytech_id": "3806",
      "person_id": "4424",
      "flags": [
        "ht-rookie"
      ]
    },
    {
      "player_id": "mhl-3571",
      "number": "5",
      "first_name": "Anton",
      "last_name": "Topilnyckyj",
      "name": "Anton Topilnyckyj",
      "position": "D",
      "height": "6'3",
      "height_inches": 75,
      "weight": 205,
      "shoots": "R",
      "birthdate": "2005-01-04",
      "birth_year": "'05",
      "age": 21,
      "hometown": "Oromocto, NB",
      "birthplace": "Oromocto, NB, NB",
      "rookie": false,
      "veteran": true,
      "headshot": "assets/headshots/Grand-Falls-Rapids/5-anton-topilnyckyj.jpg",
      "headshot_url": "https://assets.leaguestat.com/mhl/240x240/3571.jpg",
      "stats": {
        "games_played": 38,
        "goals": 3,
        "assists": 11,
        "points": 14,
        "plus_minus": 0,
        "penalty_minutes": 28,
        "power_play_goals": 0,
        "power_play_assists": 2,
        "power_play_points": 2,
        "short_handed_goals": 0,
        "short_handed_assists": 0,
        "short_handed_points": 0,
        "game_winning_goals": 0,
        "overtime_goals": 0,
        "points_per_game": 0.37
      },
      "hockeytech_id": "3571",
      "person_id": "4158",
      "flags": [
        "ht-played-major-junior"
      ]
    },
    {
      "player_id": "mhl-3411",
      "number": "6",
      "first_name": "Nathan",
      "last_name": "Dubreuil",
      "name": "Nathan Dubreuil",
      "position": "D",
      "height": "5'11",
      "height_inches": 71,
      "weight": 164,
      "shoots": "L",
      "birthdate": "2006-01-19",
      "birth_year": "'06",
      "age": 20,
      "hometown": "St-Narcisse, QC",
      "birthplace": "St-Narcisse, QC, Quebec",
      "rookie": false,
      "veteran": false,
      "headshot": "assets/headshots/Grand-Falls-Rapids/6-nathan-dubreuil.jpg",
      "headshot_url": "https://assets.leaguestat.com/mhl/240x240/3411.jpg",
      "stats": {},
      "hockeytech_id": "3411",
      "person_id": "3973",
      "flags": [
        "ht-import",
        "ht-played-major-junior"
      ]
    },
    {
      "player_id": "mhl-3399",
      "number": "7",
      "first_name": "Patrick",
      "last_name": "Baxter",
      "name": "Patrick Baxter",
      "position": "C",
      "height": "5'10",
      "height_inches": 70,
      "weight": 165,
      "shoots": "L",
      "birthdate": "2006-05-12",
      "birth_year": "'06",
      "age": 20,
      "hometown": "Moncton, NB",
      "birthplace": "Moncton, NB, ",
      "rookie": false,
      "veteran": false,
      "headshot": "assets/headshots/Grand-Falls-Rapids/7-patrick-baxter.jpg",
      "headshot_url": "https://assets.leaguestat.com/mhl/240x240/3399.jpg",
      "stats": {
        "games_played": 42,
        "goals": 12,
        "assists": 11,
        "points": 23,
        "plus_minus": 0,
        "penalty_minutes": 32,
        "power_play_goals": 0,
        "power_play_assists": 0,
        "power_play_points": 0,
        "short_handed_goals": 2,
        "short_handed_assists": 1,
        "short_handed_points": 3,
        "game_winning_goals": 1,
        "overtime_goals": 0,
        "points_per_game": 0.55
      },
      "hockeytech_id": "3399",
      "person_id": "3961",
      "flags": []
    },
    {
      "player_id": "mhl-3856",
      "number": "9",
      "first_name": "Conor",
      "last_name": "Ryan",
      "name": "Conor Ryan",
      "position": "D",
      "height": "5'10",
      "height_inches": 70,
      "weight": 170,
      "shoots": "L",
      "birthdate": "2005-10-26",
      "birth_year": "'05",
      "age": 21,
      "hometown": "St, John's, NL",
      "birthplace": "St. John's, NL, NL",
      "rookie": false,
      "veteran": false,
      "headshot": "assets/headshots/Grand-Falls-Rapids/9-conor-ryan.jpg",
      "headshot_url": "https://assets.leaguestat.com/mhl/240x240/3856.jpg",
      "stats": {
        "games_played": 34,
        "goals": 3,
        "assists": 12,
        "points": 15,
        "plus_minus": 0,
        "penalty_minutes": 18,
        "power_play_goals": 0,
        "power_play_assists": 3,
        "power_play_points": 3,
        "short_handed_goals": 0,
        "short_handed_assists": 1,
        "short_handed_points": 1,
        "game_winning_goals": 0,
        "overtime_goals": 0,
        "points_per_game": 0.44
      },
      "hockeytech_id": "3856",
      "person_id": "4484",
      "flags": []
    },
    {
      "player_id": "mhl-3318",
      "number": "10",
      "first_name": "Tristan",
      "last_name": "Richard",
      "name": "Tristan Richard",
      "position": "C",
      "height": "5'11",
      "height_inches": 71,
      "weight": 180,
      "shoots": "L",
      "birthdate": "2007-01-17",
      "birth_year": "'07",
      "age": 19,
      "hometown": "Dieppe, NB",
      "birthplace": "Dieppe, NB, ",
      "rookie": true,
      "veteran": false,
      "headshot": "assets/headshots/Grand-Falls-Rapids/10-tristan-richard.jpg",
      "headshot_url": "https://assets.leaguestat.com/mhl/240x240/3318.jpg",
      "stats": {
        "games_played": 31,
        "goals": 3,
        "assists": 7,
        "points": 10,
        "plus_minus": 0,
        "penalty_minutes": 31,
        "power_play_goals": 1,
        "power_play_assists": 0,
        "power_play_points": 1,
        "short_handed_goals": 0,
        "short_handed_assists": 0,
        "short_handed_points": 0,
        "game_winning_goals": 0,
        "overtime_goals": 0,
        "points_per_game": 0.32
      },
      "hockeytech_id": "3318",
      "person_id": "3880",
      "flags": [
        "ht-rookie"
      ]
    },
    {
      "player_id": "mhl-2794",
      "number": "12",
      "first_name": "Coen",
      "last_name": "Miller",
      "name": "Coen Miller",
      "position": "LW",
      "height": "5'11",
      "height_inches": 71,
      "weight": 165,
      "shoots": "L",
      "birthdate": "2006-02-27",
      "birth_year": "'06",
      "age": 20,
      "hometown": "Bedford, NS",
      "birthplace": "Bedford, NS, NS",
      "rookie": false,
      "veteran": false,
      "headshot": "assets/headshots/Grand-Falls-Rapids/12-coen-miller.jpg",
      "headshot_url": "https://assets.leaguestat.com/mhl/240x240/2794.jpg",
      "stats": {
        "games_played": 32,
        "goals": 22,
        "assists": 29,
        "points": 51,
        "plus_minus": 0,
        "penalty_minutes": 70,
        "power_play_goals": 9,
        "power_play_assists": 15,
        "power_play_points": 24,
        "short_handed_goals": 1,
        "short_handed_assists": 0,
        "short_handed_points": 1,
        "game_winning_goals": 5,
        "overtime_goals": 2,
        "points_per_game": 1.59
      },
      "hockeytech_id": "2794",
      "person_id": "3221",
      "flags": [
        "ht-played-major-junior"
      ]
    },
    {
      "player_id": "mhl-3784",
      "number": "16",
      "first_name": "Oliver",
      "last_name": "Plante",
      "name": "Oliver Plante",
      "position": "LW",
      "height": "5'8",
      "height_inches": 68,
      "weight": 160,
      "shoots": "L",
      "birthdate": "2007-02-28",
      "birth_year": "'07",
      "age": 19,
      "hometown": "Ottawa, ON",
      "birthplace": "Ottawa, ON, ",
      "rookie": true,
      "veteran": false,
      "headshot": "assets/headshots/Grand-Falls-Rapids/16-oliver-plante.jpg",
      "headshot_url": "https://assets.leaguestat.com/mhl/240x240/3784.jpg",
      "stats": {
        "games_played": 37,
        "goals": 8,
        "assists": 10,
        "points": 18,
        "plus_minus": 0,
        "penalty_minutes": 107,
        "power_play_goals": 0,
        "power_play_assists": 5,
        "power_play_points": 5,
        "short_handed_goals": 0,
        "short_handed_assists": 0,
        "short_handed_points": 0,
        "game_winning_goals": 2,
        "overtime_goals": 0,
        "points_per_game": 0.49
      },
      "hockeytech_id": "3784",
      "person_id": "4400",
      "flags": [
        "ht-rookie",
        "ht-import"
      ]
    },
    {
      "player_id": "mhl-3040",
      "number": "17",
      "first_name": "Isaac",
      "last_name": "Allard",
      "name": "Isaac Allard",
      "position": "D",
      "height": "6'0",
      "height_inches": 72,
      "weight": 180,
      "shoots": "L",
      "birthdate": "2005-02-14",
      "birth_year": "'05",
      "age": 21,
      "hometown": "Dieppe, NB",
      "birthplace": "Dieppe, NB, ",
      "rookie": false,
      "veteran": true,
      "headshot": "assets/headshots/Grand-Falls-Rapids/17-isaac-allard.jpg",
      "headshot_url": "https://assets.leaguestat.com/mhl/240x240/3040.jpg",
      "stats": {
        "games_played": 41,
        "goals": 7,
        "assists": 15,
        "points": 22,
        "plus_minus": 0,
        "penalty_minutes": 54,
        "power_play_goals": 1,
        "power_play_assists": 3,
        "power_play_points": 4,
        "short_handed_goals": 0,
        "short_handed_assists": 0,
        "short_handed_points": 0,
        "game_winning_goals": 0,
        "overtime_goals": 0,
        "points_per_game": 0.54
      },
      "hockeytech_id": "3040",
      "person_id": "3558",
      "flags": []
    },
    {
      "player_id": "mhl-3783",
      "number": "18",
      "first_name": "Dereck",
      "last_name": "Asselin",
      "name": "Dereck Asselin",
      "position": "C",
      "height": "5'8",
      "height_inches": 68,
      "weight": 175,
      "shoots": "L",
      "birthdate": "2007-05-14",
      "birth_year": "'07",
      "age": 19,
      "hometown": "Lévis, QC",
      "birthplace": "Lévis, QC, ",
      "rookie": true,
      "veteran": false,
      "headshot": "assets/headshots/Grand-Falls-Rapids/18-dereck-asselin.jpg",
      "headshot_url": "https://assets.leaguestat.com/mhl/240x240/3783.jpg",
      "stats": {
        "games_played": 39,
        "goals": 4,
        "assists": 11,
        "points": 15,
        "plus_minus": 0,
        "penalty_minutes": 61,
        "power_play_goals": 0,
        "power_play_assists": 0,
        "power_play_points": 0,
        "short_handed_goals": 0,
        "short_handed_assists": 0,
        "short_handed_points": 0,
        "game_winning_goals": 0,
        "overtime_goals": 0,
        "points_per_game": 0.38
      },
      "hockeytech_id": "3783",
      "person_id": "4399",
      "flags": [
        "ht-rookie",
        "ht-import"
      ]
    },
    {
      "player_id": "mhl-3150",
      "number": "21",
      "first_name": "Jonah",
      "last_name": "Leard",
      "name": "Jonah Leard",
      "position": "RW",
      "height": "5'11",
      "height_inches": 71,
      "weight": 165,
      "shoots": "R",
      "birthdate": "2006-01-31",
      "birth_year": "'06",
      "age": 20,
      "hometown": "Riverview, NB",
      "birthplace": "Riverview, NB, ",
      "rookie": false,
      "veteran": false,
      "headshot": "assets/headshots/Grand-Falls-Rapids/21-jonah-leard.jpg",
      "headshot_url": "https://assets.leaguestat.com/mhl/240x240/3150.jpg",
      "stats": {
        "games_played": 42,
        "goals": 18,
        "assists": 34,
        "points": 52,
        "plus_minus": 0,
        "penalty_minutes": 12,
        "power_play_goals": 5,
        "power_play_assists": 11,
        "power_play_points": 16,
        "short_handed_goals": 0,
        "short_handed_assists": 0,
        "short_handed_points": 0,
        "game_winning_goals": 4,
        "overtime_goals": 1,
        "points_per_game": 1.24
      },
      "hockeytech_id": "3150",
      "person_id": "3669",
      "flags": []
    },
    {
      "player_id": "mhl-2910",
      "number": "22",
      "first_name": "Bailey",
      "last_name": "Shortall",
      "name": "Bailey Shortall",
      "position": "RW",
      "height": "6'01",
      "height_inches": 73,
      "weight": 185,
      "shoots": "R",
      "birthdate": "2005-11-28",
      "birth_year": "'05",
      "age": 21,
      "hometown": "Halifax, NS",
      "birthplace": "Halifax, NS, ",
      "rookie": false,
      "veteran": false,
      "headshot": "assets/headshots/Grand-Falls-Rapids/22-bailey-shortall.jpg",
      "headshot_url": "https://assets.leaguestat.com/mhl/240x240/2910.jpg",
      "stats": {
        "games_played": 40,
        "goals": 8,
        "assists": 9,
        "points": 17,
        "plus_minus": 0,
        "penalty_minutes": 8,
        "power_play_goals": 2,
        "power_play_assists": 1,
        "power_play_points": 3,
        "short_handed_goals": 0,
        "short_handed_assists": 0,
        "short_handed_points": 0,
        "game_winning_goals": 1,
        "overtime_goals": 0,
        "points_per_game": 0.43
      },
      "hockeytech_id": "2910",
      "person_id": "3365",
      "flags": []
    },
    {
      "player_id": "mhl-3807",
      "number": "27",
      "first_name": "Mathis",
      "last_name": "Cyr",
      "name": "Mathis Cyr",
      "position": "D",
      "height": "5'10",
      "height_inches": 70,
      "weight": 175,
      "shoots": "R",
      "birthdate": "2005-07-17",
      "birth_year": "'05",
      "age": 21,
      "hometown": "Chambly, QC",
      "birthplace": "Chambly, QC, ",
      "rookie": false,
      "veteran": true,
      "headshot": "assets/headshots/Grand-Falls-Rapids/27-mathis-cyr.jpg",
      "headshot_url": "https://assets.leaguestat.com/mhl/240x240/3807.jpg",
      "stats": {
        "games_played": 35,
        "goals": 6,
        "assists": 13,
        "points": 19,
        "plus_minus": 0,
        "penalty_minutes": 14,
        "power_play_goals": 3,
        "power_play_assists": 5,
        "power_play_points": 8,
        "short_handed_goals": 0,
        "short_handed_assists": 0,
        "short_handed_points": 0,
        "game_winning_goals": 1,
        "overtime_goals": 1,
        "points_per_game": 0.54
      },
      "hockeytech_id": "3807",
      "person_id": "4425",
      "flags": [
        "ht-import"
      ]
    },
    {
      "player_id": "mhl-2853",
      "number": "28",
      "first_name": "Reid",
      "last_name": "Calder",
      "name": "Reid Calder",
      "position": "LW",
      "height": "6'1",
      "height_inches": 73,
      "weight": 198,
      "shoots": "L",
      "birthdate": "2006-03-07",
      "birth_year": "'06",
      "age": 20,
      "hometown": "Saint John, NB",
      "birthplace": "Saint John, NB, ",
      "rookie": false,
      "veteran": false,
      "headshot": "assets/headshots/Grand-Falls-Rapids/28-reid-calder.jpg",
      "headshot_url": "https://assets.leaguestat.com/mhl/240x240/2853.jpg",
      "stats": {
        "games_played": 33,
        "goals": 8,
        "assists": 8,
        "points": 16,
        "plus_minus": 0,
        "penalty_minutes": 118,
        "power_play_goals": 2,
        "power_play_assists": 0,
        "power_play_points": 2,
        "short_handed_goals": 0,
        "short_handed_assists": 0,
        "short_handed_points": 0,
        "game_winning_goals": 0,
        "overtime_goals": 0,
        "points_per_game": 0.48
      },
      "hockeytech_id": "2853",
      "person_id": "3280",
      "flags": [
        "ht-played-major-junior"
      ]
    },
    {
      "player_id": "mhl-3780",
      "number": "30",
      "first_name": "Jeremy",
      "last_name": "Thibodeau-Soucy",
      "name": "Jeremy Thibodeau-Soucy",
      "position": "G",
      "height": "6'2",
      "height_inches": 74,
      "weight": 170,
      "shoots": "L",
      "birthdate": "2007-06-29",
      "birth_year": "'07",
      "age": 19,
      "hometown": "Ste-Sophie, QC",
      "birthplace": "Ste-Sophie, QC, ",
      "rookie": true,
      "veteran": false,
      "headshot": "assets/headshots/Grand-Falls-Rapids/30-jeremy-thibodeau-soucy.jpg",
      "headshot_url": "https://assets.leaguestat.com/mhl/240x240/3780.jpg",
      "stats": {
        "games_played": 14,
        "wins": 4,
        "losses": 5,
        "ot_losses": 3,
        "minutes_played": 736,
        "saves": 336,
        "shots": 378,
        "goals_against": 42,
        "shutouts": 0,
        "save_percentage": 0.889,
        "goals_against_average": 3.43
      },
      "hockeytech_id": "3780",
      "person_id": "4396",
      "flags": [
        "ht-rookie",
        "ht-import"
      ]
    },
    {
      "player_id": "mhl-3133",
      "number": "35",
      "first_name": "Adam",
      "last_name": "Lecours",
      "name": "Adam Lecours",
      "position": "G",
      "height": "5'10",
      "height_inches": 70,
      "weight": 165,
      "shoots": "L",
      "birthdate": "2005-06-12",
      "birth_year": "'05",
      "age": 21,
      "hometown": "Sherbrooke, QC",
      "birthplace": "Sherbrooke, QC, ",
      "rookie": false,
      "veteran": true,
      "headshot": "assets/headshots/Grand-Falls-Rapids/35-adam-lecours.jpg",
      "headshot_url": "https://assets.leaguestat.com/mhl/240x240/3133.jpg",
      "stats": {
        "games_played": 31,
        "wins": 17,
        "losses": 10,
        "ot_losses": 2,
        "minutes_played": 1802,
        "saves": 901,
        "shots": 1000,
        "goals_against": 99,
        "shutouts": 2,
        "save_percentage": 0.901,
        "goals_against_average": 3.3
      },
      "hockeytech_id": "3133",
      "person_id": "3652",
      "flags": []
    },
    {
      "player_id": "mhl-2821",
      "number": "40",
      "first_name": "Brody",
      "last_name": "Pare",
      "name": "Brody Pare",
      "position": "C",
      "height": "5'10",
      "height_inches": 70,
      "weight": 170,
      "shoots": "L",
      "birthdate": "2006-08-31",
      "birth_year": "'06",
      "age": 20,
      "hometown": "Oromocto, NB",
      "birthplace": "Oromocto, NB, ",
      "rookie": false,
      "veteran": false,
      "headshot": "assets/headshots/Grand-Falls-Rapids/40-brody-pare.jpg",
      "headshot_url": "https://assets.leaguestat.com/mhl/240x240/2821.jpg",
      "stats": {
        "games_played": 39,
        "goals": 8,
        "assists": 8,
        "points": 16,
        "plus_minus": 0,
        "penalty_minutes": 61,
        "power_play_goals": 0,
        "power_play_assists": 0,
        "power_play_points": 0,
        "short_handed_goals": 1,
        "short_handed_assists": 0,
        "short_handed_points": 1,
        "game_winning_goals": 1,
        "overtime_goals": 0,
        "points_per_game": 0.41
      },
      "hockeytech_id": "2821",
      "person_id": "3248",
      "flags": []
    },
    {
      "player_id": "mhl-3921",
      "number": "55",
      "first_name": "Vincent",
      "last_name": "Robert",
      "name": "Vincent Robert",
      "position": "C",
      "height": "5\"10",
      "weight": 165,
      "shoots": "L",
      "birthdate": "2007-03-07",
      "birth_year": "'07",
      "age": 19,
      "hometown": "Lambton, QC",
      "birthplace": "Lambton, QC, ",
      "rookie": false,
      "veteran": false,
      "headshot": "assets/headshots/Grand-Falls-Rapids/55-vincent-robert.jpg",
      "headshot_url": "https://assets.leaguestat.com/mhl/240x240/3921.jpg",
      "stats": {},
      "hockeytech_id": "3921",
      "person_id": "4583",
      "flags": [
        "ht-import"
      ]
    },
    {
      "player_id": "mhl-3151",
      "number": "66",
      "first_name": "Declan",
      "last_name": "Kennedy",
      "name": "Declan Kennedy",
      "position": "C",
      "height": "5'10",
      "height_inches": 70,
      "weight": 170,
      "shoots": "L",
      "birthdate": "2007-03-30",
      "birth_year": "'07",
      "age": 19,
      "hometown": "Conception Bay South NL",
      "birthplace": "Conception Bay South NL, Conseption Bay South",
      "rookie": true,
      "veteran": false,
      "headshot": "assets/headshots/Grand-Falls-Rapids/66-declan-kennedy.jpg",
      "headshot_url": "https://assets.leaguestat.com/mhl/240x240/3151.jpg",
      "stats": {
        "games_played": 35,
        "goals": 6,
        "assists": 3,
        "points": 9,
        "plus_minus": 0,
        "penalty_minutes": 53,
        "power_play_goals": 0,
        "power_play_assists": 0,
        "power_play_points": 0,
        "short_handed_goals": 0,
        "short_handed_assists": 0,
        "short_handed_points": 0,
        "game_winning_goals": 1,
        "overtime_goals": 0,
        "points_per_game": 0.26
      },
      "hockeytech_id": "3151",
      "person_id": "3670",
      "flags": [
        "ht-rookie"
      ]
    },
    {
      "player_id": "mhl-3481",
      "number": "77",
      "first_name": "Nathan",
      "last_name": "Plamondon-Michaud",
      "name": "Nathan Plamondon-Michaud",
      "position": "C",
      "height": "6'0",
      "height_inches": 72,
      "weight": 190,
      "shoots": "R",
      "birthdate": "2005-06-22",
      "birth_year": "'05",
      "age": 21,
      "hometown": "Québec, QC",
      "birthplace": "Québec, QC, ",
      "rookie": false,
      "veteran": true,
      "headshot": "assets/headshots/Grand-Falls-Rapids/77-nathan-plamondon-michaud.jpg",
      "headshot_url": "https://assets.leaguestat.com/mhl/240x240/3481.jpg",
      "stats": {
        "games_played": 42,
        "goals": 20,
        "assists": 21,
        "points": 41,
        "plus_minus": 0,
        "penalty_minutes": 60,
        "power_play_goals": 4,
        "power_play_assists": 9,
        "power_play_points": 13,
        "short_handed_goals": 1,
        "short_handed_assists": 0,
        "short_handed_points": 1,
        "game_winning_goals": 3,
        "overtime_goals": 1,
        "points_per_game": 0.98
      },
      "hockeytech_id": "3481",
      "person_id": "4044",
      "flags": [
        "ht-import",
        "ht-played-major-junior"
      ]
    },
    {
      "player_id": "mhl-3805",
      "number": "91",
      "first_name": "Loic",
      "last_name": "Francoeur",
      "name": "Loic Francoeur",
      "position": "C",
      "height": "6'2",
      "height_inches": 74,
      "weight": 195,
      "shoots": "L",
      "birthdate": "2005-06-05",
      "birth_year": "'05",
      "age": 21,
      "hometown": "St-Jean-sur-Richelieu, QC",
      "birthplace": "St-Jean-sur-Richelieu, QC, ",
      "rookie": false,
      "veteran": true,
      "headshot": "assets/headshots/Grand-Falls-Rapids/91-loic-francoeur.jpg",
      "headshot_url": "https://assets.leaguestat.com/mhl/240x240/3805.jpg",
      "stats": {
        "games_played": 40,
        "goals": 17,
        "assists": 28,
        "points": 45,
        "plus_minus": 0,
        "penalty_minutes": 20,
        "power_play_goals": 8,
        "power_play_assists": 12,
        "power_play_points": 20,
        "short_handed_goals": 1,
        "short_handed_assists": 0,
        "short_handed_points": 1,
        "game_winning_goals": 2,
        "overtime_goals": 0,
        "points_per_game": 1.13
      },
      "hockeytech_id": "3805",
      "person_id": "4423",
      "flags": [
        "ht-import",
        "ht-played-major-junior"
      ]
    },
    {
      "player_id": "mhl-3423",
      "number": "99",
      "first_name": "Simon",
      "last_name": "Bourque",
      "name": "Simon Bourque",
      "position": "C",
      "height": "5'11",
      "height_inches": 71,
      "weight": 180,
      "shoots": "R",
      "birthdate": "2008-03-01",
      "birth_year": "'08",
      "age": 18,
      "hometown": "Dieppe, NB",
      "birthplace": "Dieppe, NB, ",
      "rookie": false,
      "veteran": false,
      "stats": {},
      "hockeytech_id": "3423",
      "person_id": "3986",
      "flags": [
        "ht-affiliate"
      ]
    },
    {
      "player_id": "mhl-undefined",
      "name": "Unknown Player",
      "rookie": false,
      "veteran": false,
      "stats": {
        "games_played": 42,
        "wins": 21,
        "losses": 15,
        "ot_losses": 5,
        "minutes_played": 2556,
        "saves": 1237,
        "shots": 1388,
        "goals_against": 151,
        "shutouts": 2,
        "save_percentage": 0.891,
        "goals_against_average": 3.54
      },
      "flags": []
    }
  ]
}