{
  "team_slug": "miramichi-timberwolves",
  "team_name": "Miramichi-Timberwolves",
  "league": "MHL",
  "season": "2024-25",
  "season_id": 41,
  "team_id": 9,
  "updated_at": "2025-11-19T06:51:08.832Z",
  "player_count": 25,
  "players": [
    {
      "player_id": "mhl-3494",
      "number": "6",
      "first_name": "Lorenzo",
      "last_name": "Tita",
      "name": "Lorenzo Tita",
      "position": "C",
      "height": "5'10",
      "height_inches": 70,
      "weight": 170,
      "shoots": "L",
      "birthdate": "2006-02-20",
      "birth_year": "'06",
      "age": 19,
      "hometown": "Stroudsburg, PA USA",
      "birthplace": "Stroudsburg, PA USA, ",
      "rookie": false,
      "veteran": false,
      "headshot": "assets/headshots/Miramichi-Timberwolves/6-lorenzo-tita.jpg",
      "headshot_url": "https://assets.leaguestat.com/mhl/240x240/3494.jpg",
      "stats": {
        "games_played": 19,
        "goals": 6,
        "assists": 7,
        "points": 13,
        "plus_minus": 0,
        "penalty_minutes": 2,
        "power_play_goals": 0,
        "power_play_assists": 2,
        "power_play_points": 2,
        "short_handed_goals": 0,
        "short_handed_assists": 0,
        "short_handed_points": 0,
        "game_winning_goals": 0,
        "overtime_goals": 0,
        "points_per_game": 0.68
      },
      "hockeytech_id": "3494",
      "person_id": "4057",
      "flags": [
        "ht-import"
      ]
    },
    {
      "player_id": "mhl-3817",
      "number": "7",
      "first_name": "Olivier",
      "last_name": "Théberge",
      "name": "Olivier Théberge",
      "position": "D",
      "height": "6'1",
      "height_inches": 73,
      "weight": 196,
      "shoots": "L",
      "birthdate": "2005-01-13",
      "birth_year": "'05",
      "age": 20,
      "hometown": "Québec, QC",
      "birthplace": "Québec, QC, ",
      "rookie": false,
      "veteran": false,
      "headshot": "assets/headshots/Miramichi-Timberwolves/7-olivier-th-berge.jpg",
      "headshot_url": "https://assets.leaguestat.com/mhl/240x240/3817.jpg",
      "stats": {
        "games_played": 20,
        "goals": 5,
        "assists": 4,
        "points": 9,
        "plus_minus": 0,
        "penalty_minutes": 42,
        "power_play_goals": 2,
        "power_play_assists": 4,
        "power_play_points": 6,
        "short_handed_goals": 0,
        "short_handed_assists": 0,
        "short_handed_points": 0,
        "game_winning_goals": 1,
        "overtime_goals": 0,
        "points_per_game": 0.45
      },
      "hockeytech_id": "3817",
      "person_id": "4435",
      "flags": [
        "ht-import",
        "ht-played-major-junior"
      ]
    },
    {
      "player_id": "mhl-3349",
      "number": "8",
      "first_name": "Cameron",
      "last_name": "LeBlanc",
      "name": "Cameron LeBlanc",
      "position": "D",
      "height": "5'11",
      "height_inches": 71,
      "weight": 174,
      "shoots": "R",
      "birthdate": "2008-07-24",
      "birth_year": "'08",
      "age": 17,
      "hometown": "Rogersville, NB",
      "birthplace": "Rogersville, NB, ",
      "rookie": true,
      "veteran": false,
      "headshot": "assets/headshots/Miramichi-Timberwolves/8-cameron-leblanc.jpg",
      "headshot_url": "https://assets.leaguestat.com/mhl/240x240/3349.jpg",
      "stats": {
        "games_played": 19,
        "goals": 0,
        "assists": 3,
        "points": 3,
        "plus_minus": 0,
        "penalty_minutes": 6,
        "power_play_goals": 0,
        "power_play_assists": 0,
        "power_play_points": 0,
        "short_handed_goals": 0,
        "short_handed_assists": 0,
        "short_handed_points": 0,
        "game_winning_goals": 0,
        "overtime_goals": 0,
        "points_per_game": 0.16
      },
      "hockeytech_id": "3349",
      "person_id": "3911",
      "flags": [
        "ht-rookie"
      ]
    },
    {
      "player_id": "mhl-3791",
      "number": "9",
      "first_name": "Alexis",
      "last_name": "Doucet",
      "name": "Alexis Doucet",
      "position": "RW",
      "height": "6'0",
      "height_inches": 72,
      "weight": 183,
      "shoots": "R",
      "birthdate": "2006-01-09",
      "birth_year": "'06",
      "age": 19,
      "hometown": "Trois-Rivières, QC",
      "birthplace": "Trois-Rivières, QC, ",
      "rookie": false,
      "veteran": false,
      "headshot": "assets/headshots/Miramichi-Timberwolves/9-alexis-doucet.jpg",
      "headshot_url": "https://assets.leaguestat.com/mhl/240x240/3791.jpg",
      "stats": {
        "games_played": 21,
        "goals": 13,
        "assists": 11,
        "points": 24,
        "plus_minus": 0,
        "penalty_minutes": 34,
        "power_play_goals": 3,
        "power_play_assists": 5,
        "power_play_points": 8,
        "short_handed_goals": 1,
        "short_handed_assists": 0,
        "short_handed_points": 1,
        "game_winning_goals": 2,
        "overtime_goals": 0,
        "points_per_game": 1.14
      },
      "hockeytech_id": "3791",
      "person_id": "4409",
      "flags": [
        "ht-import",
        "ht-played-major-junior"
      ]
    },
    {
      "player_id": "mhl-3278",
      "number": "10",
      "first_name": "Eliott",
      "last_name": "Robert",
      "name": "Eliott Robert",
      "position": "LW",
      "height": "6'0",
      "height_inches": 72,
      "weight": 185,
      "shoots": "R",
      "birthdate": "2005-05-09",
      "birth_year": "'05",
      "age": 20,
      "hometown": "Trois-Rivières, QC",
      "birthplace": "Trois-Rivières, QC, QC",
      "rookie": false,
      "veteran": false,
      "headshot": "assets/headshots/Miramichi-Timberwolves/10-eliott-robert.jpg",
      "headshot_url": "https://assets.leaguestat.com/mhl/240x240/3278.jpg",
      "stats": {
        "games_played": 21,
        "goals": 11,
        "assists": 14,
        "points": 25,
        "plus_minus": 0,
        "penalty_minutes": 28,
        "power_play_goals": 2,
        "power_play_assists": 2,
        "power_play_points": 4,
        "short_handed_goals": 1,
        "short_handed_assists": 0,
        "short_handed_points": 1,
        "game_winning_goals": 0,
        "overtime_goals": 0,
        "points_per_game": 1.19
      },
      "hockeytech_id": "3278",
      "person_id": "3833",
      "flags": [
        "ht-played-major-junior"
      ]
    },
    {
      "player_id": "mhl-3777",
      "number": "11",
      "first_name": "Thomas",
      "last_name": "Guérard",
      "name": "Thomas Guérard",
      "position": "LW",
      "height": "5'9",
      "height_inches": 69,
      "weight": 185,
      "shoots": "L",
      "birthdate": "2007-03-06",
      "birth_year": "'07",
      "age": 18,
      "hometown": "St-Boniface, QC",
      "birthplace": "St-Boniface, QC, ",
      "rookie": true,
      "veteran": false,
      "headshot": "assets/headshots/Miramichi-Timberwolves/11-thomas-gu-rard.jpg",
      "headshot_url": "https://assets.leaguestat.com/mhl/240x240/3777.jpg",
      "stats": {
        "games_played": 9,
        "goals": 0,
        "assists": 1,
        "points": 1,
        "plus_minus": 0,
        "penalty_minutes": 21,
        "power_play_goals": 0,
        "power_play_assists": 0,
        "power_play_points": 0,
        "short_handed_goals": 0,
        "short_handed_assists": 0,
        "short_handed_points": 0,
        "game_winning_goals": 0,
        "overtime_goals": 0,
        "points_per_game": 0.11
      },
      "hockeytech_id": "3777",
      "person_id": "4393",
      "flags": [
        "ht-rookie",
        "ht-import"
      ]
    },
    {
      "player_id": "mhl-3338",
      "number": "12",
      "first_name": "Grady",
      "last_name": "Burns",
      "name": "Grady Burns",
      "position": "C",
      "height": "5'11",
      "height_inches": 71,
      "weight": 175,
      "shoots": "R",
      "birthdate": "2008-04-25",
      "birth_year": "'08",
      "age": 17,
      "hometown": "Miramichi, NB",
      "birthplace": "Miramichi. NB, ",
      "rookie": true,
      "veteran": false,
      "headshot": "assets/headshots/Miramichi-Timberwolves/12-grady-burns.jpg",
      "headshot_url": "https://assets.leaguestat.com/mhl/240x240/3338.jpg",
      "stats": {
        "games_played": 19,
        "goals": 1,
        "assists": 2,
        "points": 3,
        "plus_minus": 0,
        "penalty_minutes": 6,
        "power_play_goals": 0,
        "power_play_assists": 0,
        "power_play_points": 0,
        "short_handed_goals": 0,
        "short_handed_assists": 0,
        "short_handed_points": 0,
        "game_winning_goals": 1,
        "overtime_goals": 0,
        "points_per_game": 0.16
      },
      "hockeytech_id": "3338",
      "person_id": "3900",
      "flags": [
        "ht-rookie"
      ]
    },
    {
      "player_id": "mhl-2442",
      "number": "14",
      "first_name": "Mitchell",
      "last_name": "Wagner",
      "name": "Mitchell Wagner",
      "position": "RW",
      "height": "6'5",
      "height_inches": 77,
      "weight": 205,
      "shoots": "R",
      "birthdate": "2005-03-01",
      "birth_year": "'05",
      "age": 20,
      "hometown": "Beaver Bank, NS",
      "birthplace": "Beaver Bank, NS, ",
      "rookie": false,
      "veteran": false,
      "headshot": "assets/headshots/Miramichi-Timberwolves/14-mitchell-wagner.jpg",
      "headshot_url": "https://assets.leaguestat.com/mhl/240x240/2442.jpg",
      "stats": {},
      "hockeytech_id": "2442",
      "person_id": "2834",
      "flags": [
        "ht-played-major-junior"
      ]
    },
    {
      "player_id": "mhl-3223",
      "number": "17",
      "first_name": "Ryan",
      "last_name": "Hackett",
      "name": "Ryan Hackett",
      "position": "D",
      "height": "5'11",
      "height_inches": 71,
      "weight": 175,
      "shoots": "L",
      "birthdate": "2005-09-06",
      "birth_year": "'05",
      "age": 20,
      "hometown": "Barnaby River, NB",
      "birthplace": "Barnaby River, NB, ",
      "rookie": false,
      "veteran": false,
      "headshot": "assets/headshots/Miramichi-Timberwolves/17-ryan-hackett.jpg",
      "headshot_url": "https://assets.leaguestat.com/mhl/240x240/3223.jpg",
      "stats": {
        "games_played": 20,
        "goals": 1,
        "assists": 6,
        "points": 7,
        "plus_minus": 0,
        "penalty_minutes": 8,
        "power_play_goals": 1,
        "power_play_assists": 3,
        "power_play_points": 4,
        "short_handed_goals": 0,
        "short_handed_assists": 0,
        "short_handed_points": 0,
        "game_winning_goals": 0,
        "overtime_goals": 0,
        "points_per_game": 0.35
      },
      "hockeytech_id": "3223",
      "person_id": "3752",
      "flags": [
        "ht-played-major-junior"
      ]
    },
    {
      "player_id": "mhl-3709",
      "number": "18",
      "first_name": "Aiden",
      "last_name": "Clowater",
      "name": "Aiden Clowater",
      "position": "LW",
      "height": "5'10",
      "height_inches": 70,
      "weight": 175,
      "shoots": "L",
      "birthdate": "2007-07-17",
      "birth_year": "'07",
      "age": 18,
      "hometown": "Middle Sackville, NS",
      "birthplace": "Middle Sackville, NS, ",
      "rookie": true,
      "veteran": false,
      "headshot": "assets/headshots/Miramichi-Timberwolves/18-aiden-clowater.jpg",
      "headshot_url": "https://assets.leaguestat.com/mhl/240x240/3709.jpg",
      "stats": {
        "games_played": 21,
        "goals": 2,
        "assists": 1,
        "points": 3,
        "plus_minus": 0,
        "penalty_minutes": 4,
        "power_play_goals": 0,
        "power_play_assists": 0,
        "power_play_points": 0,
        "short_handed_goals": 0,
        "short_handed_assists": 0,
        "short_handed_points": 0,
        "game_winning_goals": 2,
        "overtime_goals": 0,
        "points_per_game": 0.14
      },
      "hockeytech_id": "3709",
      "person_id": "4324",
      "flags": [
        "ht-rookie"
      ]
    },
    {
      "player_id": "mhl-2848",
      "number": "19",
      "first_name": "Nick",
      "last_name": "Beatty",
      "name": "Nick Beatty",
      "position": "LW",
      "height": "5'11",
      "height_inches": 71,
      "weight": 175,
      "shoots": "L",
      "birthdate": "2005-10-24",
      "birth_year": "'05",
      "age": 20,
      "hometown": "Quispamsis, NB",
      "birthplace": "Quispamsis, NB, NB",
      "rookie": false,
      "veteran": false,
      "headshot": "assets/headshots/Miramichi-Timberwolves/19-nick-beatty.jpg",
      "headshot_url": "https://assets.leaguestat.com/mhl/240x240/2848.jpg",
      "stats": {
        "games_played": 20,
        "goals": 0,
        "assists": 5,
        "points": 5,
        "plus_minus": 0,
        "penalty_minutes": 10,
        "power_play_goals": 0,
        "power_play_assists": 1,
        "power_play_points": 1,
        "short_handed_goals": 0,
        "short_handed_assists": 0,
        "short_handed_points": 0,
        "game_winning_goals": 0,
        "overtime_goals": 0,
        "points_per_game": 0.25
      },
      "hockeytech_id": "2848",
      "person_id": "3275",
      "flags": []
    },
    {
      "player_id": "mhl-2797",
      "number": "20",
      "first_name": "Nolan",
      "last_name": "Ryan",
      "name": "Nolan Ryan",
      "position": "D",
      "height": "5'9",
      "height_inches": 69,
      "weight": 170,
      "shoots": "R",
      "birthdate": "2006-04-06",
      "birth_year": "'06",
      "age": 19,
      "hometown": "Hampton, NB",
      "birthplace": "Hampton, NB, ",
      "rookie": false,
      "veteran": false,
      "headshot": "assets/headshots/Miramichi-Timberwolves/20-nolan-ryan.jpg",
      "headshot_url": "https://assets.leaguestat.com/mhl/240x240/2797.jpg",
      "stats": {
        "games_played": 20,
        "goals": 0,
        "assists": 3,
        "points": 3,
        "plus_minus": 0,
        "penalty_minutes": 64,
        "power_play_goals": 0,
        "power_play_assists": 0,
        "power_play_points": 0,
        "short_handed_goals": 0,
        "short_handed_assists": 0,
        "short_handed_points": 0,
        "game_winning_goals": 0,
        "overtime_goals": 0,
        "points_per_game": 0.15
      },
      "hockeytech_id": "2797",
      "person_id": "3224",
      "flags": []
    },
    {
      "player_id": "mhl-3792",
      "number": "22",
      "first_name": "Benoit",
      "last_name": "Arsenault",
      "name": "Benoit Arsenault",
      "position": "D",
      "height": "6'2",
      "height_inches": 74,
      "weight": 198,
      "shoots": "L",
      "birthdate": "2006-04-27",
      "birth_year": "'06",
      "age": 19,
      "hometown": "Lévis, QC",
      "birthplace": "Lévis, QC, ",
      "rookie": true,
      "veteran": false,
      "headshot": "assets/headshots/Miramichi-Timberwolves/22-benoit-arsenault.jpg",
      "headshot_url": "https://assets.leaguestat.com/mhl/240x240/3792.jpg",
      "stats": {},
      "hockeytech_id": "3792",
      "person_id": "4410",
      "flags": [
        "ht-rookie",
        "ht-import"
      ]
    },
    {
      "player_id": "mhl-3207",
      "number": "23",
      "first_name": "Ryan",
      "last_name": "Hayes",
      "name": "Ryan Hayes",
      "position": "D",
      "height": "6'3",
      "height_inches": 75,
      "weight": 195,
      "shoots": "L",
      "birthdate": "2005-05-16",
      "birth_year": "'05",
      "age": 20,
      "hometown": "Port Hawkesbury, NS",
      "birthplace": "Port Hawkesbury, NS, ",
      "rookie": false,
      "veteran": false,
      "headshot": "assets/headshots/Miramichi-Timberwolves/23-ryan-hayes.jpg",
      "headshot_url": "https://assets.leaguestat.com/mhl/240x240/3207.jpg",
      "stats": {
        "games_played": 19,
        "goals": 2,
        "assists": 6,
        "points": 8,
        "plus_minus": 0,
        "penalty_minutes": 45,
        "power_play_goals": 1,
        "power_play_assists": 2,
        "power_play_points": 3,
        "short_handed_goals": 0,
        "short_handed_assists": 0,
        "short_handed_points": 0,
        "game_winning_goals": 0,
        "overtime_goals": 0,
        "points_per_game": 0.42
      },
      "hockeytech_id": "3207",
      "person_id": "3728",
      "flags": []
    },
    {
      "player_id": "mhl-3342",
      "number": "24",
      "first_name": "Dawson",
      "last_name": "Peverelle",
      "name": "Dawson Peverelle",
      "position": "LW",
      "height": "5'9",
      "height_inches": 69,
      "weight": 150,
      "shoots": "L",
      "birthdate": "2008-10-04",
      "birth_year": "'08",
      "age": 17,
      "hometown": "Bridgewater, NS",
      "birthplace": "Bridgewater, NS, ",
      "rookie": true,
      "veteran": false,
      "headshot": "assets/headshots/Miramichi-Timberwolves/24-dawson-peverelle.jpg",
      "headshot_url": "https://assets.leaguestat.com/mhl/240x240/3342.jpg",
      "stats": {
        "games_played": 21,
        "goals": 4,
        "assists": 5,
        "points": 9,
        "plus_minus": 0,
        "penalty_minutes": 18,
        "power_play_goals": 0,
        "power_play_assists": 0,
        "power_play_points": 0,
        "short_handed_goals": 0,
        "short_handed_assists": 0,
        "short_handed_points": 0,
        "game_winning_goals": 1,
        "overtime_goals": 0,
        "points_per_game": 0.43
      },
      "hockeytech_id": "3342",
      "person_id": "3904",
      "flags": [
        "ht-rookie"
      ]
    },
    {
      "player_id": "mhl-2900",
      "number": "26",
      "first_name": "Kaden",
      "last_name": "McNeil",
      "name": "Kaden McNeil",
      "position": "D",
      "height": "6'3",
      "height_inches": 75,
      "weight": 205,
      "shoots": "R",
      "birthdate": "2006-03-13",
      "birth_year": "'06",
      "age": 19,
      "hometown": "Renous, NB",
      "birthplace": "Renous, NB, ",
      "rookie": false,
      "veteran": false,
      "headshot": "assets/headshots/Miramichi-Timberwolves/26-kaden-mcneil.jpg",
      "headshot_url": "https://assets.leaguestat.com/mhl/240x240/2900.jpg",
      "stats": {
        "games_played": 21,
        "goals": 1,
        "assists": 11,
        "points": 12,
        "plus_minus": 0,
        "penalty_minutes": 20,
        "power_play_goals": 1,
        "power_play_assists": 2,
        "power_play_points": 3,
        "short_handed_goals": 0,
        "short_handed_assists": 0,
        "short_handed_points": 0,
        "game_winning_goals": 0,
        "overtime_goals": 0,
        "points_per_game": 0.57
      },
      "hockeytech_id": "2900",
      "person_id": "3346",
      "flags": []
    },
    {
      "player_id": "mhl-3173",
      "number": "27",
      "first_name": "Harlan",
      "last_name": "Eustace",
      "name": "Harlan Eustace",
      "position": "RW",
      "height": "5'9",
      "height_inches": 69,
      "weight": 187,
      "shoots": "L",
      "birthdate": "2007-04-17",
      "birth_year": "'07",
      "age": 18,
      "hometown": "Riverview, NB",
      "birthplace": "Riverview, NB, ",
      "rookie": true,
      "veteran": false,
      "headshot": "assets/headshots/Miramichi-Timberwolves/27-harlan-eustace.jpg",
      "headshot_url": "https://assets.leaguestat.com/mhl/240x240/3173.jpg",
      "stats": {
        "games_played": 20,
        "goals": 5,
        "assists": 6,
        "points": 11,
        "plus_minus": 0,
        "penalty_minutes": 6,
        "power_play_goals": 1,
        "power_play_assists": 1,
        "power_play_points": 2,
        "short_handed_goals": 0,
        "short_handed_assists": 0,
        "short_handed_points": 0,
        "game_winning_goals": 0,
        "overtime_goals": 0,
        "points_per_game": 0.55
      },
      "hockeytech_id": "3173",
      "person_id": "3693",
      "flags": [
        "ht-rookie"
      ]
    },
    {
      "player_id": "mhl-3790",
      "number": "28",
      "first_name": "Charles-Olivier",
      "last_name": "Giguère",
      "name": "Charles-Olivier Giguère",
      "position": "RW",
      "height": "6'3",
      "height_inches": 75,
      "weight": 181,
      "shoots": "R",
      "birthdate": "2007-02-01",
      "birth_year": "'07",
      "age": 18,
      "hometown": "Victoriaville, QC",
      "birthplace": "Victoriaville, QC, ",
      "rookie": true,
      "veteran": false,
      "headshot": "assets/headshots/Miramichi-Timberwolves/28-charles-olivier-gigu-re.jpg",
      "headshot_url": "https://assets.leaguestat.com/mhl/240x240/3790.jpg",
      "stats": {
        "games_played": 21,
        "goals": 2,
        "assists": 7,
        "points": 9,
        "plus_minus": 0,
        "penalty_minutes": 20,
        "power_play_goals": 0,
        "power_play_assists": 3,
        "power_play_points": 3,
        "short_handed_goals": 0,
        "short_handed_assists": 0,
        "short_handed_points": 0,
        "game_winning_goals": 0,
        "overtime_goals": 0,
        "points_per_game": 0.43
      },
      "hockeytech_id": "3790",
      "person_id": "4408",
      "flags": [
        "ht-rookie",
        "ht-import"
      ]
    },
    {
      "player_id": "mhl-3334",
      "number": "31",
      "first_name": "Mathis",
      "last_name": "Lafontaine",
      "name": "Mathis Lafontaine",
      "position": "G",
      "height": "5'10",
      "height_inches": 70,
      "weight": 170,
      "shoots": "L",
      "birthdate": "2006-06-12",
      "birth_year": "'06",
      "age": 19,
      "hometown": "Trois-Rivieres, QC",
      "birthplace": "Trois-Rivieres, QC, ",
      "rookie": false,
      "veteran": false,
      "headshot": "assets/headshots/Miramichi-Timberwolves/31-mathis-lafontaine.jpg",
      "headshot_url": "https://assets.leaguestat.com/mhl/240x240/3334.jpg",
      "stats": {
        "games_played": 6,
        "wins": 2,
        "losses": 4,
        "ot_losses": 0,
        "minutes_played": 310,
        "saves": 137,
        "shots": 151,
        "goals_against": 14,
        "shutouts": 1,
        "save_percentage": 0.907,
        "goals_against_average": 2.71
      },
      "hockeytech_id": "3334",
      "person_id": "3896",
      "flags": [
        "ht-import"
      ]
    },
    {
      "player_id": "mhl-2953",
      "number": "33",
      "first_name": "Jack",
      "last_name": "Flanagan",
      "name": "Jack Flanagan",
      "position": "G",
      "height": "6'4",
      "height_inches": 76,
      "weight": 200,
      "shoots": "L",
      "birthdate": "2005-02-08",
      "birth_year": "'05",
      "age": 20,
      "hometown": "Saint John, NB",
      "birthplace": "Saint John, NB, ",
      "rookie": false,
      "veteran": false,
      "headshot": "assets/headshots/Miramichi-Timberwolves/33-jack-flanagan.jpg",
      "headshot_url": "https://assets.leaguestat.com/mhl/240x240/2953.jpg",
      "stats": {
        "games_played": 17,
        "wins": 8,
        "losses": 6,
        "ot_losses": 0,
        "minutes_played": 956,
        "saves": 505,
        "shots": 558,
        "goals_against": 53,
        "shutouts": 2,
        "save_percentage": 0.905,
        "goals_against_average": 3.33
      },
      "hockeytech_id": "2953",
      "person_id": "3426",
      "flags": [
        "ht-played-major-junior"
      ]
    },
    {
      "player_id": "mhl-3178",
      "number": "37",
      "first_name": "Thatcher",
      "last_name": "Hughes",
      "name": "Thatcher Hughes",
      "position": "LW",
      "height": "5'9",
      "height_inches": 69,
      "weight": 150,
      "shoots": "L",
      "birthdate": "2006-11-18",
      "birth_year": "'06",
      "age": 19,
      "hometown": "Charlottetown, PE",
      "birthplace": "Charlottetown, PE, ",
      "rookie": false,
      "veteran": false,
      "headshot": "assets/headshots/Miramichi-Timberwolves/37-thatcher-hughes.jpg",
      "headshot_url": "https://assets.leaguestat.com/mhl/240x240/3178.jpg",
      "stats": {
        "games_played": 21,
        "goals": 11,
        "assists": 10,
        "points": 21,
        "plus_minus": 0,
        "penalty_minutes": 25,
        "power_play_goals": 3,
        "power_play_assists": 0,
        "power_play_points": 3,
        "short_handed_goals": 0,
        "short_handed_assists": 0,
        "short_handed_points": 0,
        "game_winning_goals": 1,
        "overtime_goals": 0,
        "points_per_game": 1
      },
      "hockeytech_id": "3178",
      "person_id": "3698",
      "flags": []
    },
    {
      "player_id": "mhl-2635",
      "number": "71",
      "first_name": "Jacob",
      "last_name": "Kaine",
      "name": "Jacob Kaine",
      "position": "C",
      "height": "5'10",
      "height_inches": 70,
      "weight": 152,
      "shoots": "R",
      "birthdate": "2005-11-07",
      "birth_year": "'05",
      "age": 20,
      "hometown": "Quispamsis, NB",
      "birthplace": "Quispamsis, NB, NB",
      "rookie": false,
      "veteran": false,
      "headshot": "assets/headshots/Miramichi-Timberwolves/71-jacob-kaine.jpg",
      "headshot_url": "https://assets.leaguestat.com/mhl/240x240/2635.jpg",
      "stats": {
        "games_played": 21,
        "goals": 6,
        "assists": 13,
        "points": 19,
        "plus_minus": 0,
        "penalty_minutes": 14,
        "power_play_goals": 1,
        "power_play_assists": 4,
        "power_play_points": 5,
        "short_handed_goals": 0,
        "short_handed_assists": 0,
        "short_handed_points": 0,
        "game_winning_goals": 0,
        "overtime_goals": 0,
        "points_per_game": 0.9
      },
      "hockeytech_id": "2635",
      "person_id": "3059",
      "flags": [
        "ht-played-major-junior"
      ]
    },
    {
      "player_id": "mhl-3847",
      "number": "99",
      "first_name": "Cooper",
      "last_name": "Burns",
      "name": "Cooper Burns",
      "position": "G",
      "height": "6'2",
      "height_inches": 74,
      "weight": 210,
      "shoots": "L",
      "birthdate": "2009-05-30",
      "birth_year": "'09",
      "age": 16,
      "hometown": "Miramichi, NB",
      "birthplace": "Miramichi, NB, ",
      "rookie": true,
      "veteran": false,
      "stats": {
        "games_played": 0,
        "wins": 0,
        "losses": 0,
        "ot_losses": 0,
        "minutes_played": 0,
        "saves": 0,
        "shots": 0,
        "goals_against": 0,
        "shutouts": 0,
        "save_percentage": 0,
        "goals_against_average": 0
      },
      "hockeytech_id": "3847",
      "person_id": "4475",
      "flags": [
        "ht-rookie",
        "ht-affiliate"
      ]
    },
    {
      "player_id": "mhl-3346",
      "number": "99",
      "first_name": "Zavier",
      "last_name": "Roy",
      "name": "Zavier Roy",
      "position": "G",
      "height": "5'10",
      "height_inches": 70,
      "weight": 160,
      "shoots": "L",
      "birthdate": "2008-04-05",
      "birth_year": "'08",
      "age": 17,
      "hometown": "Beresford, NB",
      "birthplace": "Beresford, NB, ",
      "rookie": true,
      "veteran": false,
      "stats": {
        "games_played": 0,
        "wins": 0,
        "losses": 0,
        "ot_losses": 0,
        "minutes_played": 0,
        "saves": 0,
        "shots": 0,
        "goals_against": 0,
        "shutouts": 0,
        "save_percentage": 0,
        "goals_against_average": 0
      },
      "hockeytech_id": "3346",
      "person_id": "3908",
      "flags": [
        "ht-rookie",
        "ht-affiliate"
      ]
    },
    {
      "player_id": "mhl-undefined",
      "name": "Unknown Player",
      "rookie": false,
      "veteran": false,
      "stats": {
        "games_played": 21,
        "wins": 10,
        "losses": 10,
        "ot_losses": 0,
        "minutes_played": 1274,
        "saves": 642,
        "shots": 714,
        "goals_against": 72,
        "shutouts": 4,
        "save_percentage": 0.899,
        "goals_against_average": 3.39
      },
      "flags": []
    }
  ]
}